README.md
setup.cfg
setup.py
settings_manager/__init__.py
settings_manager/json.py
settings_manager/manager.py
settings_manager/python.py
settings_manager/utils.py
settings_manager/yaml.py
settings_manager.egg-info/PKG-INFO
settings_manager.egg-info/SOURCES.txt
settings_manager.egg-info/dependency_links.txt
settings_manager.egg-info/not-zip-safe
settings_manager.egg-info/requires.txt
settings_manager.egg-info/top_level.txt