Metadata-Version: 2.1
Name: settings-manager
Version: 0.1.2
Summary: A settings manager for python applications
Home-page: https://github.com/DataDaoDe/py-settings-manager
Author: John Faucett
Author-email: jwaterfaucett@gmail.com
License: MIT
Platform: UNKNOWN
Classifier: Programming Language :: Python :: 3
Classifier: Development Status :: 3 - Alpha
Classifier: License :: OSI Approved :: MIT License
Classifier: Operating System :: OS Independent
Requires-Python: >= 3.6
